rtcom/__init__.py
rtcom/rtcom.py
rtcom/utils.py
rtcom-0.1.5.dist-info/AUTHORS.rst
rtcom-0.1.5.dist-info/LICENSE
rtcom-0.1.5.dist-info/METADATA
rtcom-0.1.5.dist-info/WHEEL
rtcom-0.1.5.dist-info/top_level.txt
rtcom-0.1.5.dist-info/RECORD
