Metadata-Version: 2.1
Name: rtcom
Version: 0.1.5
Summary: Real Time Communication Library for home robotics and automation. 
Home-page: https://github.com/rjean/rtcom
Author: Raphael Jean
Author-email: raphael.jean@rocketmail.com
License: MIT license
Keywords: rtcom
Platform: UNKNOWN
Classifier: Development Status :: 2 - Pre-Alpha
Classifier: Intended Audience :: Developers
Classifier: License :: OSI Approved :: MIT License
Classifier: Natural Language :: English
Classifier: Programming Language :: Python :: 3
Classifier: Programming Language :: Python :: 3.6
Classifier: Programming Language :: Python :: 3.7
Classifier: Programming Language :: Python :: 3.8
Requires-Python: >=3.6
